[
  {
    "id": 1,
    "name": "Antman",
    "image": "./images/antman.png"
  },
  {
    "id": 2,
    "name": "Black Panther",
    "image": "./images/blackpanther.png"
  },
  {
    "id": 3,
    "name": "Blackwidow",
    "image": "./images/blackwidow.png"
  },
  {
    "id": 4,
    "name": "Captain Marvel",
    "image": "./images/capmarvel.png"
  },
  {
    "id": 5,
    "name": "Captain America",
    "image": "./images/capamerica.png"
  },
  {
    "id": 6,
    "name": "Dr Strange",
    "image": "./images/drstrange.png"
  },
  {
    "id": 7,
    "name": "Falcon",
    "image": "./images/falcon.png"
  },
  {
    "id": 8,
    "name": "Hawkeye",
    "image": "./images/hawkeye.png"
  },
  {
    "id": 9,
    "name": "Hulk",
    "image": "./images/hulk.png"
  },
  {
    "id": 10,
    "name": "Ironman",
    "image": "./images/ironman.png"
  },
  {
    "id": 11,
    "name": "Spderman",
    "image": "./images/spiderman.png"
  },
  {
    "id": 12,
    "name": "Thor",
    "image": "./images/thor.png"
  }
]
